LICENSE
MANIFEST.in
README.md
carbonate_sync.py
setup.cfg
setup.py
carbonate_utils.egg-info/PKG-INFO
carbonate_utils.egg-info/SOURCES.txt
carbonate_utils.egg-info/dependency_links.txt
carbonate_utils.egg-info/entry_points.txt
carbonate_utils.egg-info/requires.txt
carbonate_utils.egg-info/top_level.txt