Metadata-Version: 1.0
Name: carbonate-utils
Version: 0.4.0
Summary: Tools for tools for managing federated carbon clusters.
Home-page: https://github.com/criteo/carbonate-utils
Author: Corentin Chary
Author-email: c.chary@criteo.com
License: MIT
Keywords: graphite carbon carbonate
Platform: UNKNOWN
